maskedtensor/__init__.py
maskedtensor/binary.py
maskedtensor/core.py
maskedtensor/creation.py
maskedtensor/functions.py
maskedtensor/matmul.py
maskedtensor/passthrough.py
maskedtensor/reductions.py
maskedtensor/unary.py
maskedtensor_test-0.10.0.dist-info/LICENSE
maskedtensor_test-0.10.0.dist-info/METADATA
maskedtensor_test-0.10.0.dist-info/WHEEL
maskedtensor_test-0.10.0.dist-info/top_level.txt
maskedtensor_test-0.10.0.dist-info/zip-safe
maskedtensor_test-0.10.0.dist-info/RECORD
