Metadata-Version: 2.1
Name: maskedtensor-test
Version: 0.10.0
Summary: MaskedTensors for PyTorch
Home-page: https://github.com/cpuhrsch/maskedtensor
Author: Christian Puhrsch
Author-email: cpuhrsch@fb.com
License: UNKNOWN
Platform: UNKNOWN
Classifier: Programming Language :: Python :: 3
Classifier: Operating System :: OS Independent
License-File: LICENSE
Requires-Dist: torch (<1.12,>=1.11)
